pymw/__init__.py
pymw/_api.py
pymw-0.9.1.dist-info/LICENSE
pymw-0.9.1.dist-info/METADATA
pymw-0.9.1.dist-info/WHEEL
pymw-0.9.1.dist-info/top_level.txt
pymw-0.9.1.dist-info/zip-safe
pymw-0.9.1.dist-info/RECORD
