Metadata-Version: 2.1
Name: pymw
Version: 0.9.1
Summary: A thin MediaWiki client using requests.
Home-page: https://github.com/5j9/pymw
Author: 5j9
Author-email: 5j9@users.noreply.github.com
License: GNU General Public License v3 (GPLv3)
Platform: UNKNOWN
Classifier: Development Status :: 1 - Planning
Classifier: Intended Audience :: Developers
Classifier: License :: OSI Approved :: GNU General Public License v3 (GPLv3)
Classifier: Natural Language :: English
Classifier: Programming Language :: Python :: 3.9
Classifier: Environment :: Web Environment
Requires-Python: >=3.9
Requires-Dist: requests
